CHANGES.txt
ZPL.txt
setup.cfg
setup.py
bibliograph/__init__.py
bibliograph.parsing.egg-info/PKG-INFO
bibliograph.parsing.egg-info/SOURCES.txt
bibliograph.parsing.egg-info/dependency_links.txt
bibliograph.parsing.egg-info/entry_points.txt
bibliograph.parsing.egg-info/namespace_packages.txt
bibliograph.parsing.egg-info/not-zip-safe
bibliograph.parsing.egg-info/requires.txt
bibliograph.parsing.egg-info/top_level.txt
bibliograph/parsing/README.txt
bibliograph/parsing/TODO.txt
bibliograph/parsing/__init__.py
bibliograph/parsing/configure.zcml
bibliograph/parsing/interfaces.py
bibliograph/parsing/parsers/__init__.py
bibliograph/parsing/parsers/base.py
bibliograph/parsing/parsers/bibtex.py
bibliograph/parsing/parsers/endnote.py
bibliograph/parsing/parsers/medline.py
bibliograph/parsing/parsers/ris.py
bibliograph/parsing/parsers/xml.py
bibliograph/parsing/tests/__init__.py
bibliograph/parsing/tests/base.py
bibliograph/parsing/tests/setup.py
bibliograph/parsing/tests/test_base.py
bibliograph/parsing/tests/test_bibtex_parsing.py
bibliograph/parsing/tests/test_endnote_parser.py
bibliograph/parsing/tests/test_medline_parser.py
bibliograph/parsing/tests/test_ris_parser.py
bibliograph/parsing/tests/test_xml_parser.py
bibliograph/parsing/tests/samples/bibtex_test.bib
bibliograph/parsing/tests/samples/bibtex_test2.bib
bibliograph/parsing/tests/samples/bibtex_test3.bib
bibliograph/parsing/tests/samples/bibtex_test_cite_key.bib
bibliograph/parsing/tests/samples/bibtex_test_duplicates.bib
bibliograph/parsing/tests/samples/bibtex_test_inbookreferences.bib
bibliograph/parsing/tests/samples/bibtex_test_lastfieldkomma.bib
bibliograph/parsing/tests/samples/bibtex_test_multiauthors.bib
bibliograph/parsing/tests/samples/bibtex_test_typefield.bib
bibliograph/parsing/tests/samples/cmfbat-pdffile1.pdf
bibliograph/parsing/tests/samples/cmfbat-pdffile2.pdf
bibliograph/parsing/tests/samples/cmfbat-pdffile3.pdf
bibliograph/parsing/tests/samples/endnote.end
bibliograph/parsing/tests/samples/idcooking_test.bib
bibliograph/parsing/tests/samples/medline_test.bib
bibliograph/parsing/tests/samples/medline_test.med
bibliograph/parsing/tests/samples/medline_test.xml
bibliograph/parsing/tests/samples/pdffolder_test.bib
bibliograph/parsing/tests/samples/ris_test.ris
bibliograph/parsing/tests/samples/umlauts.xml