Metadata-Version: 1.0
Name: bibliograph.parsing
Version: 1.0.1
Summary: Parsers for bibliograph packages
Home-page: http://svn.plone.org/svn/collective/bibliograph.parsing/
Author: Paul Bugni, Cris Ewing
Author-email: plone-biblio@das-netzwerkteam.de
License: ZPL 2.1
Keywords: bibtex bibliography xml endnote ris bibutils parsers
Platform: UNKNOWN
Classifier: Framework :: Plone
Classifier: Framework :: Zope2
Classifier: Framework :: Zope3
Classifier: Programming Language :: Python
Classifier: Development Status :: 5 - Production/Stable
Classifier: Topic :: Software Development :: Libraries :: Python Modules
